pyraymesh-0.2.6.dist-info/WHEEL
pyraymesh-0.2.6.dist-info/RECORD
pyraymesh-0.2.6.dist-info/METADATA
pyraymesh-0.2.6.dist-info/licenses/LICENSE
pyraymesh/_bvh_bind_ext.cpython-313-i386-linux-gnu.so
pyraymesh/Mesh.py
pyraymesh/py.typed
pyraymesh/IntersectionResult.py
pyraymesh/__init__.py
pyraymesh/ray_functions.py
