Metadata-Version: 2.2
Name: pyraymesh
Version: 0.2.6
Summary: A library for ray-mesh intersections on triangular meshes
Author-Email: =?utf-8?q?Dag_W=C3=A4stberg?= <dwastberg@gmail.com>
License: MIT
Classifier: Development Status :: 4 - Beta
Classifier: License :: OSI Approved :: MIT License
Classifier: Programming Language :: Python :: 3
Classifier: Topic :: Software Development :: Libraries
Classifier: Topic :: Scientific/Engineering :: Mathematics
Project-URL: homepage, https://github.com/dwastberg/pyraymesh
Requires-Python: >=3.10
Requires-Dist: numpy
